Metadata-Version: 1.0
Name: che-guevara-otp
Version: 2021.11.4.210
Summary: Python OTP
Home-page: https://github.com/wdbm/che_guevara_otp
Author: Will Breaden Madden
Author-email: wbm@protonmail.ch
License: GPLv3
Platform: UNKNOWN
